rtql8/ExpressionParser.py
rtql8/ExpressionValidator.py
rtql8/__init__.py
rtql8/cli.py
rtql8-0.1.1.dist-info/METADATA
rtql8-0.1.1.dist-info/WHEEL
rtql8-0.1.1.dist-info/entry_points.txt
rtql8-0.1.1.dist-info/RECORD
