Metadata-Version: 2.3
Name: rtql8
Version: 0.1.1
Summary: RTQL8 a given cron expression
Author: KellyDC
Author-email: kelly.carinola@gmail.com
Requires-Python: >=3.13
Classifier: Programming Language :: Python :: 3
Classifier: Programming Language :: Python :: 3.13
Requires-Dist: argparse (>=1.4.0,<2.0.0)
